retinal_thin_vessels/__init__.py
retinal_thin_vessels/core.py
retinal_thin_vessels/get_relation.py
retinal_thin_vessels/input_transformation.py
retinal_thin_vessels/metrics.py
retinal_thin_vessels/weights.py
retinal_thin_vessels/external/DSE_skeleton_pruning/setup.py
retinal_thin_vessels/external/DSE_skeleton_pruning/dsepruning/__init__.py
retinal_thin_vessels/external/DSE_skeleton_pruning/dsepruning/dsepruning.py
retinal_thin_vessels-2.0.dist-info/licenses/LICENSE
retinal_thin_vessels-2.0.dist-info/METADATA
retinal_thin_vessels-2.0.dist-info/WHEEL
retinal_thin_vessels-2.0.dist-info/top_level.txt
retinal_thin_vessels-2.0.dist-info/RECORD
