Metadata-Version: 2.4
Name: retinal_thin_vessels
Version: 2.0
Summary: A Python package for analyzing thin retinal vessels and creating vessels-thickness based weight maps
Author-email: João Paulo Menezes Linaris <joaolinaris@gmail.com>
License-Expression: MIT
Project-URL: Homepage, https://github.com/J-Linaris/retinal_thin_vessels
Project-URL: Repository, https://github.com/J-Linaris/retinal_thin_vessels
Keywords: retina,retinal,retinal-vessels,vessel-segmentation,image-analysis,medical-imaging,deep-learning,weight-map,pytorch,thin-vessels,image-segmentation,binary-masks,binary-mask
Classifier: Intended Audience :: Science/Research
Classifier: Operating System :: POSIX :: Linux
Classifier: Programming Language :: Python :: 3
Classifier: Programming Language :: Python :: 3.8
Classifier: Programming Language :: Python :: 3.9
Classifier: Programming Language :: Python :: 3.10
Classifier: Programming Language :: Python :: 3.11
Classifier: Programming Language :: Python :: 3.12
Requires-Python: >=3.8
License-File: LICENSE
Requires-Dist: numpy
Requires-Dist: torch
Requires-Dist: scikit-image
Requires-Dist: scikit-learn
Requires-Dist: Pillow
Dynamic: license-file
